setup.py
verne_probability/Binomialdistribution.py
verne_probability/Gaussiandistribution.py
verne_probability/Generaldistribution.py
verne_probability/__init__.py
verne_probability.egg-info/PKG-INFO
verne_probability.egg-info/SOURCES.txt
verne_probability.egg-info/dependency_links.txt
verne_probability.egg-info/not-zip-safe
verne_probability.egg-info/top_level.txt