Metadata-Version: 1.0
Name: verne-probability
Version: 0.1
Summary: Gaussian and Binomial Distributions
Home-page: UNKNOWN
Author: Verne Ongteco
Author-email: UNKNOWN
License: UNKNOWN
Platform: UNKNOWN
